{
  "version": 1,
  "serviceConfiguration": {
    "apiName": "limewerx",
    "serviceName": "AppSync",
    "gqlSchemaPath": "/tmp/amplify-83c53205-859c-466b-90ef-debf6a18d89d/amplify/backend/api/limewerx/schema.graphql",
    "defaultAuthType": {
      "mode": "API_KEY",
      "keyDescription": "api key description",
      "expirationTime": 30
    },
    "conflictResolution": {
      "defaultResolutionStrategy": {
        "type": "AUTOMERGE"
      }
    },
    "additionalAuthTypes": [
      {
        "mode": "AWS_IAM"
      },
      {
        "mode": "AMAZON_COGNITO_USER_POOLS",
        "cognitoUserPoolId": "authlimewerx"
      }
    ]
  }
}